a_unet/__init__.py
a_unet/apex.py
a_unet/blocks.py
a_unet-0.0.16.dist-info/LICENSE
a_unet-0.0.16.dist-info/METADATA
a_unet-0.0.16.dist-info/WHEEL
a_unet-0.0.16.dist-info/top_level.txt
a_unet-0.0.16.dist-info/RECORD
